faultless/__init__.py
faultless-1.0.1.dist-info/WHEEL
faultless-1.0.1.dist-info/LICENSE
faultless-1.0.1.dist-info/METADATA
faultless-1.0.1.dist-info/RECORD
